AUTHORS
Changelog
INSTALL
LICENSE
MANIFEST.in
README
THANKS
TODO
setup.cfg
setup.py
django_kombu.egg-info/PKG-INFO
django_kombu.egg-info/SOURCES.txt
django_kombu.egg-info/dependency_links.txt
django_kombu.egg-info/not-zip-safe
django_kombu.egg-info/top_level.txt
djkombu/__init__.py
djkombu/__init__.pyc
djkombu/managers.py
djkombu/models.py
djkombu/transport.py
djkombu/management/__init__.py
djkombu/management/commands/__init__.py
djkombu/management/commands/clean_kombu_messages.py