Metadata-Version: 1.0
Name: django-kombu
Version: 0.9.2
Summary: Kombu transport using the Django database as a message store.
Home-page: http://github.com/ask/django-kombu/
Author: Ask Solem
Author-email: ask@celeryproject.org
License: BSD
Platform: any
Classifier: Development Status :: 4 - Beta
Classifier: Operating System :: OS Independent
Classifier: Programming Language :: Python
Classifier: Intended Audience :: Developers
Classifier: Topic :: Software Development :: Libraries :: Python Modules
